{"fetchTime":1655337331820,"posts":[{"title":"见义勇为与囚徒困境","url":"/t/859904","author":"sNullp","node_url":"/go/random","node_name":"随想","replies":8,"avatar_url":"https://cdn.v2ex.com/avatar/52c5/1893/1637_large.png?m=1642209587","last_touched":"2022-06-16 07:10:35 +08:00","last_reply_by":"sidkang"},{"title":"618 MBP 外接键盘推荐","url":"/t/859905","author":"YoungKing6","node_url":"/go/apple","node_name":"Apple","replies":1,"avatar_url":"https://cdn.v2ex.com/avatar/87ed/7214/495591_large.png?m=1635077020","last_touched":"2022-06-16 07:21:44 +08:00","last_reply_by":"ericbize"},{"title":"MAC 电脑两个触控板分别控制两个屏幕的一些思考","url":"/t/859899","author":"jayce789","node_url":"/go/apple","node_name":"Apple","replies":6,"avatar_url":"https://cdn.v2ex.com/gravatar/56b5063d55015b9b59e20095dde00a59?s=48&d=retro","last_touched":"2022-06-16 07:13:04 +08:00","last_reply_by":"yyfearth"},{"title":"Windows 应用如何自动下一步安装？","url":"/t/859895","author":"dicken","node_url":"/go/eggpain","node_name":"强迫症","replies":5,"avatar_url":"https://cdn.v2ex.com/gravatar/426035b75f8d475d0dfaa8a3c884d4be?s=48&d=retro","last_touched":"2022-06-16 02:52:41 +08:00","last_reply_by":"Lightbright"},{"title":"20220616 午夜俱乐部","url":"/t/859897","author":"sciel","node_url":"/go/afterdark","node_name":"天黑以后","replies":3,"avatar_url":"https://cdn.v2ex.com/avatar/2daa/04a4/555132_xlarge.png?m=1655103185","last_touched":"2022-06-16 01:27:47 +08:00","last_reply_by":"learningman"},{"title":"要不要换工作？求骂醒","url":"/t/859896","author":"AlohaW","node_url":"/go/qna","node_name":"问与答","replies":2,"avatar_url":"https://cdn.v2ex.com/gravatar/618b11cc34d4d0f927d137a11b4bf784?s=48&d=retro","last_touched":"2022-06-16 06:25:00 +08:00","last_reply_by":"jadec0der"},{"title":"Obsidian 数据损坏 control character null","url":"/t/859903","author":"tubie","node_url":"/go/qna","node_name":"问与答","replies":1,"avatar_url":"https://cdn.v2ex.com/avatar/9f5a/1437/19979_xlarge.png?m=1653993600","last_touched":"2022-06-16 04:25:11 +08:00","last_reply_by":"dingwen07"},{"title":"Apple Watch 的一个恶性 Bug,站立检测不到","url":"/t/859901","author":"LZWDRWEB","node_url":"/go/watch","node_name":" WATCH","replies":0,"avatar_url":"https://cdn.v2ex.com/avatar/c0d0/0439/233381_xlarge.png?m=1655315860","last_touched":"2022-06-16 01:59:38 +08:00","last_reply_by":""},{"title":"脱离考试后，我不会写长文了。","url":"/t/859861","author":"Salticey","node_url":"/go/life","node_name":"生活","replies":15,"avatar_url":"https://cdn.v2ex.com/avatar/c608/4947/389889_large.png?m=1648041212","last_touched":"2022-06-15 23:33:39 +08:00","last_reply_by":"hs0000t"},{"title":"给 MBP 加了散热垫，确实可以冲，最实际的效果是风扇安静了。。。","url":"/t/859883","author":"easonl","node_url":"/go/mbp","node_name":"MacBook Pro","replies":11,"avatar_url":"https://cdn.v2ex.com/avatar/9f6d/ebc7/370570_large.png?m=1578163881","last_touched":"2022-06-16 03:15:27 +08:00","last_reply_by":"ttys001"},{"title":"PVE 的管理页面是自签证书 https 的，如何借助 frp 外网访问？","url":"/t/859872","author":"AllenHua","node_url":"/go/programmer","node_name":"程序员","replies":15,"avatar_url":"https://cdn.v2ex.com/avatar/ec19/3600/274670_large.png?m=1640074464","last_touched":"2022-06-15 23:11:06 +08:00","last_reply_by":"documentzhangx66"},{"title":"上海电信宽带拆机必须本人身份证到场合理吗","url":"/t/859867","author":"nznd","node_url":"/go/bb","node_name":"宽带症候群","replies":14,"avatar_url":"https://cdn.v2ex.com/gravatar/5bdebe5b035331641989449c3b15a86d?s=48&d=retro","last_touched":"2022-06-15 22:29:13 +08:00","last_reply_by":"iceblacksmith"},{"title":"收集一下大家敲代码深度使用的笔记本","url":"/t/859878","author":"codingBug","node_url":"/go/qna","node_name":"问与答","replies":12,"avatar_url":"https://cdn.v2ex.com/avatar/e801/1069/374481_large.png?m=1655300520","last_touched":"2022-06-16 03:48:59 +08:00","last_reply_by":"shuimugan"},{"title":"想在 github 上发布某视频监控产品的漏洞/设计缺陷","url":"/t/859889","author":"Chaconne","node_url":"/go/programmer","node_name":"程序员","replies":12,"avatar_url":"https://cdn.v2ex.com/gravatar/d6ae37d6db56fa6288b8b85408a9d706?s=48&d=retro","last_touched":"2022-06-16 01:02:14 +08:00","last_reply_by":"Les1ie"},{"title":"怎么查看一款 steam 游戏是用什么工具/语言开发的？","url":"/t/859871","author":"2232588429","node_url":"/go/qna","node_name":"问与答","replies":5,"avatar_url":"https://cdn.v2ex.com/avatar/e141/5faa/40182_large.png?m=1654480491","last_touched":"2022-06-16 00:53:38 +08:00","last_reply_by":"fatigue"},{"title":"出个 GitHub 账号会有人要么","url":"/t/859888","author":"tozp","node_url":"/go/share","node_name":"分享发现","replies":5,"avatar_url":"https://cdn.v2ex.com/gravatar/b244b8f35aa2fe064d21f80f6e1aa27c?s=48&d=retro","last_touched":"2022-06-16 01:13:44 +08:00","last_reply_by":"lizhiqing"},{"title":"打开 zoom 出现 zoom.com.cn，而不是 zoom.us，怎么解决？","url":"/t/859863","author":"JasonLaw","node_url":"/go/qna","node_name":"问与答","replies":7,"avatar_url":"https://cdn.v2ex.com/gravatar/4fdf59ece7cd78f432ec513634889579?s=48&d=retro","last_touched":"2022-06-15 22:22:46 +08:00","last_reply_by":"JasonLaw"},{"title":"写了一个用于手动屏蔽敏感信息的轻量 js 库","url":"/t/859862","author":"hc93","node_url":"/go/create","node_name":"分享创造","replies":0,"avatar_url":"https://cdn.v2ex.com/avatar/a79d/0612/326310_xlarge.png?m=1655297249","last_touched":"2022-06-15 20:23:15 +08:00","last_reply_by":""},{"title":"win 本盒盖后，怎么样能让外接显示屏仍然显示扩展屏幕？","url":"/t/859886","author":"xd880616","node_url":"/go/qna","node_name":"问与答","replies":6,"avatar_url":"https://cdn.v2ex.com/gravatar/7de9290cfaea98456fdccd7f32041f73?s=48&d=retro","last_touched":"2022-06-16 01:05:06 +08:00","last_reply_by":"Osk"},{"title":"有没有老哥能介绍在日本的 it 工作","url":"/t/859860","author":"ghostwind","node_url":"/go/tokyo","node_name":"东京","replies":5,"avatar_url":"https://cdn.v2ex.com/gravatar/dd515f751552689a497e72ce74439ee2?s=48&d=retro","last_touched":"2022-06-15 21:39:07 +08:00","last_reply_by":"lingyan190"},{"title":"es 插入索引的正常性能应该是多少？","url":"/t/859879","author":"winRain","node_url":"/go/elasticsearch","node_name":"Elasticsearch","replies":2,"avatar_url":"https://cdn.v2ex.com/gravatar/413ff2f54c115fdf1d5a004c3be167ce?s=48&d=retro","last_touched":"2022-06-15 23:16:50 +08:00","last_reply_by":"strawberryBug"},{"title":"项目仓库大文件存储方式","url":"/t/859890","author":"hardwork","node_url":"/go/qna","node_name":"问与答","replies":5,"avatar_url":"https://cdn.v2ex.com/gravatar/a82a6d88d490cb9319b36e5bacddbb60?s=48&d=retro","last_touched":"2022-06-16 01:53:14 +08:00","last_reply_by":"lizhiqing"},{"title":"[Windows 11 22H2 排雷] 不想说脏话, 但微软的 UX 设计师能不能给平板用户留一条活路?","url":"/t/859864","author":"Osk","node_url":"/go/windows","node_name":"Windows","replies":4,"avatar_url":"https://cdn.v2ex.com/avatar/fb42/34b9/102941_large.png?m=1653711034","last_touched":"2022-06-16 00:55:09 +08:00","last_reply_by":"Osk"},{"title":"iPhone13 iOS15.5 微信 8.0.23 进入微信有时候屏幕触控失灵","url":"/t/859885","author":"luoxiaolei","node_url":"/go/iphone","node_name":"iPhone","replies":4,"avatar_url":"https://cdn.v2ex.com/avatar/074c/5aac/196616_xlarge.png?m=1651850277","last_touched":"2022-06-15 23:17:22 +08:00","last_reply_by":"Dachunlv"},{"title":"iPhone se 3 能通过耳机播放杜比全景声吗","url":"/t/859865","author":"edr1412","node_url":"/go/apple","node_name":"Apple","replies":3,"avatar_url":"https://cdn.v2ex.com/gravatar/be6182f61fb7a41e19b1f65cd2f91925?s=48&d=retro","last_touched":"2022-06-15 22:25:04 +08:00","last_reply_by":"edr1412"},{"title":"网站运维工程师（影视类、视频网站）：年薪 18w 起步，单休，远程工作：","url":"/t/859902","author":"dongfengchuanmei","node_url":"/go/jobs","node_name":"酷工作","replies":0,"avatar_url":"https://cdn.v2ex.com/avatar/c843/1c13/583661_xlarge.png?m=1654321179","last_touched":"2022-06-16 02:42:12 +08:00","last_reply_by":""},{"title":"为啥我的 watch SE 没电了后再次充电就要重新恢复初始配置一次","url":"/t/859866","author":"chainwithyou","node_url":"/go/watch","node_name":" WATCH","replies":2,"avatar_url":"https://cdn.v2ex.com/avatar/4460/113c/565609_xlarge.png?m=1646301738","last_touched":"2022-06-15 22:15:42 +08:00","last_reply_by":"wangpao"},{"title":"有在 wxg 的大佬吗？帮我给提这个功能的人喂坨****","url":"/t/859891","author":"kiko12324","node_url":"/go/wechat","node_name":"微信","replies":2,"avatar_url":"https://cdn.v2ex.com/avatar/38a2/8fd7/551700_large.png?m=1655308537","last_touched":"2022-06-16 00:38:04 +08:00","last_reply_by":"westoy"},{"title":"playcover 在 12.4 上运行软件闪退","url":"/t/859868","author":"shinonome","node_url":"/go/macos","node_name":"macOS","replies":0,"avatar_url":"https://cdn.v2ex.com/avatar/95cd/d1ef/496702_xlarge.png?m=1642488738","last_touched":"2022-06-15 20:50:28 +08:00","last_reply_by":""},{"title":"时隔两年,我总算又把 inline amp 主题更新了一下","url":"/t/859873","author":"hhacker","node_url":"/go/wordpress","node_name":"WordPress","replies":0,"avatar_url":"https://cdn.v2ex.com/gravatar/0f691ff71dab8d7bdd215b23619767fb?s=48&d=retro","last_touched":"2022-06-15 21:03:06 +08:00","last_reply_by":""},{"title":"请问 GPW 一代 和 anywhere 3 哪一款鼠标在 MacBook 上体验好一点？","url":"/t/859875","author":"psyer","node_url":"/go/qna","node_name":"问与答","replies":0,"avatar_url":"https://cdn.v2ex.com/avatar/930e/4c09/499687_large.png?m=1649574835","last_touched":"2022-06-15 21:05:01 +08:00","last_reply_by":""},{"title":"kernel_task 流量异常","url":"/t/859892","author":"admin268","node_url":"/go/macos","node_name":"macOS","replies":0,"avatar_url":"https://cdn.v2ex.com/gravatar/27edfc68f4aef13cd7f879142d3cf780?s=48&d=retro","last_touched":"2022-06-15 23:57:25 +08:00","last_reply_by":""},{"title":"[Shenzhen] Quality Assurance Engineer ( Python )","url":"/t/859900","author":"Julia96","node_url":"/go/jobs","node_name":"酷工作","replies":0,"avatar_url":"https://cdn.v2ex.com/gravatar/343c838960af6ed625f6203f5f9abe86?s=48&d=retro","last_touched":"2022-06-16 01:39:58 +08:00","last_reply_by":""},{"title":"上海-不加班-外企 招 Java ， 高级 C++，中高级安卓，高级性能测试，中级支持工程师，帮忙内推成功送 5000","url":"/t/859877","author":"xsldebugger0020","node_url":"/go/jobs","node_name":"酷工作","replies":0,"avatar_url":"https://cdn.v2ex.com/gravatar/93f0a50f28d541199618be7a7ff760c2?s=48&d=retro","last_touched":"2022-06-15 21:35:52 +08:00","last_reply_by":""},{"title":"作为一名二本计算机专业的教师，如何点亮学生的技能树","url":"/t/859822","author":"bbsabc2","node_url":"/go/programmer","node_name":"程序员","replies":97,"avatar_url":"https://cdn.v2ex.com/avatar/a9ca/423b/454880_large.png?m=1592527569","last_touched":"2022-06-16 06:40:33 +08:00","last_reply_by":"chasb"},{"title":"在德国快十年了，应该回国吗？","url":"/t/859858","author":"lovdanny","node_url":"/go/qna","node_name":"问与答","replies":113,"avatar_url":"https://cdn.v2ex.com/avatar/a169/1bc8/69730_large.png?m=1633773418","last_touched":"2022-06-16 07:12:10 +08:00","last_reply_by":"pangpre"},{"title":"有没有公司的产品是基于多家公有云的。一家云出了问题，可以平滑切换到其他云计算厂商？","url":"/t/859841","author":"j717273419","node_url":"/go/cloud","node_name":"云计算","replies":30,"avatar_url":"https://cdn.v2ex.com/avatar/593d/e40b/31149_large.png?m=1442644604","last_touched":"2022-06-16 07:16:35 +08:00","last_reply_by":"elfive"},{"title":"ios 记账软件推荐","url":"/t/859837","author":"proxytoworld","node_url":"/go/qna","node_name":"问与答","replies":24,"avatar_url":"https://cdn.v2ex.com/avatar/5e55/4696/481415_large.png?m=1651761065","last_touched":"2022-06-16 00:28:49 +08:00","last_reply_by":"Kawauso"},{"title":"中信银行信用卡","url":"/t/859807","author":"dicc","node_url":"/go/share","node_name":"分享发现","replies":26,"avatar_url":"https://cdn.v2ex.com/gravatar/9738782174db30aeb1917ce310343a59?s=48&d=retro","last_touched":"2022-06-16 06:02:41 +08:00","last_reply_by":"love2328"},{"title":"无法通过反射将 interface{}转换成结构题的问题","url":"/t/859806","author":"zmqiang","node_url":"/go/go","node_name":"Go 编程语言","replies":10,"avatar_url":"https://cdn.v2ex.com/avatar/df4b/2536/207766_large.png?m=1655280803","last_touched":"2022-06-15 23:06:33 +08:00","last_reply_by":"Buges"},{"title":"求推荐适合单人玩的 pc 端游戏大作","url":"/t/859824","author":"imxiaoi","node_url":"/go/games","node_name":"游戏","replies":16,"avatar_url":"https://cdn.v2ex.com/gravatar/aab5fe2267cf2c8f00218bcdf633f93b?s=48&d=retro","last_touched":"2022-06-16 05:50:33 +08:00","last_reply_by":"Mac"},{"title":"请教一个 web 接口设计","url":"/t/859840","author":"darnurash","node_url":"/go/java","node_name":"Java","replies":14,"avatar_url":"https://cdn.v2ex.com/avatar/34f7/ed0c/87678_large.png?m=1424607068","last_touched":"2022-06-15 22:14:57 +08:00","last_reply_by":"DonaldY"},{"title":"有大佬知道解析音乐文件的开源库吗？","url":"/t/859808","author":"deweixu","node_url":"/go/programmer","node_name":"程序员","replies":4,"avatar_url":"https://cdn.v2ex.com/avatar/c1d8/b087/164546_large.png?m=1651911601","last_touched":"2022-06-15 23:13:56 +08:00","last_reply_by":"wudicgi"},{"title":"今天突然调配出了一个非常不错味道的果汁饮料","url":"/t/859852","author":"israinbow","node_url":"/go/taste","node_name":"美酒与美食","replies":6,"avatar_url":"https://cdn.v2ex.com/avatar/f072/b90e/508029_xlarge.png?m=1654447612","last_touched":"2022-06-15 21:29:44 +08:00","last_reply_by":"rabbbit"},{"title":"[高考毕业]求笔记本电脑推荐","url":"/t/859828","author":"DuDuDu0o0","node_url":"/go/edu","node_name":"教育","replies":10,"avatar_url":"https://cdn.v2ex.com/gravatar/f9f83b89824f646274c2417549e884f4?s=48&d=retro","last_touched":"2022-06-16 01:31:38 +08:00","last_reply_by":"qyd0801"},{"title":"离开鹅厂第三年，个人开发的 VR 游戏安装破百万了！","url":"/t/859846","author":"liuhanyang0","node_url":"/go/games","node_name":"游戏","replies":4,"avatar_url":"https://cdn.v2ex.com/avatar/f889/fb1a/97164_large.png?m=1426128515","last_touched":"2022-06-15 22:39:12 +08:00","last_reply_by":"gainsurier"},{"title":"相亲对象生日，有啥子比较适合的礼物推荐吗？预算五百以内。","url":"/t/859832","author":"rocliu2020","node_url":"/go/qna","node_name":"问与答","replies":18,"avatar_url":"https://cdn.v2ex.com/gravatar/98f9f9bc95b7b727a5f49e651bef3709?s=48&d=retro","last_touched":"2022-06-15 23:01:29 +08:00","last_reply_by":"ibxcme"},{"title":"请问一下 去哪可以找个设计师，设计网站里的图片 logo 等素材，除了某八戒某宝等","url":"/t/859820","author":"zzzmh","node_url":"/go/qna","node_name":"问与答","replies":10,"avatar_url":"https://cdn.v2ex.com/avatar/36a9/2909/403095_large.png?m=1640654984","last_touched":"2022-06-15 18:00:39 +08:00","last_reply_by":"learnshare"},{"title":"关于 KVM 主机网络问题请教","url":"/t/859833","author":"a1274598858","node_url":"/go/cloud","node_name":"云计算","replies":7,"avatar_url":"https://cdn.v2ex.com/avatar/1704/6096/377344_large.png?m=1609377778","last_touched":"2022-06-16 00:10:00 +08:00","last_reply_by":"debuggerx"}]}