{"fetchTime":1655682908497,"posts":[{"title":"WeChatPlayer.exe 进程 CPU 占用过高","url":"/t/860756","author":"einsdisp","node_url":"/go/programmer","node_name":"程序员","replies":0,"avatar_url":"https://cdn.v2ex.com/gravatar/7533125b485db2a9a75aa3571c736e8c?s=48&d=retro","last_touched":"2022-06-20 07:45:02 +08:00","last_reply_by":""},{"title":"原生 Android 系统，当连接 WiFi 网络无法连接互联网时，如何自动用 4G 上网","url":"/t/860755","author":"yuedashi","node_url":"/go/programmer","node_name":"程序员","replies":4,"avatar_url":"https://cdn.v2ex.com/gravatar/6d0fb16f09707dd2c420dda9a2a51eb2?s=48&d=retro","last_touched":"2022-06-20 07:43:38 +08:00","last_reply_by":"HankAviator"},{"title":"新版本 IDEA 如何处理控制台中文输出乱码的问题？","url":"/t/860741","author":"Richard14","node_url":"/go/java","node_name":"Java","replies":15,"avatar_url":"https://cdn.v2ex.com/avatar/c6a9/667a/531423_xlarge.png?m=1650751424","last_touched":"2022-06-20 07:30:18 +08:00","last_reply_by":"Richard14"},{"title":"腾讯云轻量服务器有没有办法跨账号内网互联？","url":"/t/860752","author":"RatioPattern","node_url":"/go/cloud","node_name":"云计算","replies":4,"avatar_url":"https://cdn.v2ex.com/avatar/23ea/ed19/568767_xlarge.png?m=1641974029","last_touched":"2022-06-20 07:27:39 +08:00","last_reply_by":"RatioPattern"},{"title":"我惊呆了。。。CSDN VIP 月卡 88 元","url":"/t/860634","author":"PopRain","node_url":"/go/programmer","node_name":"程序员","replies":46,"avatar_url":"https://cdn.v2ex.com/avatar/52e6/5864/442967_large.png?m=1571234314","last_touched":"2022-06-20 06:13:22 +08:00","last_reply_by":"frankies"},{"title":"LeetCode 的 Java 题目，同样的数据，本地能过测试但是在线过不了","url":"/t/860705","author":"movq","node_url":"/go/programmer","node_name":"程序员","replies":23,"avatar_url":"https://cdn.v2ex.com/avatar/046c/e28c/463491_xlarge.png?m=1645235637","last_touched":"2022-06-20 06:08:06 +08:00","last_reply_by":"pengtdyd"},{"title":"2022 年 MBP M2 256G SSD 工作够不够用？","url":"/t/860528","author":"INBreeze","node_url":"/go/programmer","node_name":"程序员","replies":49,"avatar_url":"https://cdn.v2ex.com/gravatar/13a12578c2abe2b83756ec48c2079b4e?s=48&d=retro","last_touched":"2022-06-20 00:52:28 +08:00","last_reply_by":"Actrace"},{"title":"Cpp 移动构造函数的问题","url":"/t/860731","author":"woshichuanqilz","node_url":"/go/programmer","node_name":"程序员","replies":14,"avatar_url":"https://cdn.v2ex.com/avatar/2c38/70c1/139700_large.png?m=1639713450","last_touched":"2022-06-20 02:30:23 +08:00","last_reply_by":"Buges"},{"title":"两盘位群晖 basic 模式，升级其中一块硬盘的最佳方式是什么？","url":"/t/860730","author":"sy61008317","node_url":"/go/nas","node_name":"NAS","replies":2,"avatar_url":"https://cdn.v2ex.com/gravatar/c9e403c0398440cfa8e7b0833fa76920?s=48&d=retro","last_touched":"2022-06-20 00:30:10 +08:00","last_reply_by":"lepig"},{"title":"第一次 NPM 造轮子，看看有什么注意点","url":"/t/860654","author":"iqoo","node_url":"/go/programmer","node_name":"程序员","replies":15,"avatar_url":"https://cdn.v2ex.com/avatar/91b9/d36b/555363_large.png?m=1652954437","last_touched":"2022-06-19 23:16:24 +08:00","last_reply_by":"hamsterbase"},{"title":"求教一个 sql 优化问题","url":"/t/860721","author":"zephyru","node_url":"/go/mysql","node_name":"MySQL","replies":3,"avatar_url":"https://cdn.v2ex.com/avatar/011a/e90b/347227_large.png?m=1655646722","last_touched":"2022-06-20 06:24:02 +08:00","last_reply_by":"pengtdyd"},{"title":"Windows 上面到底有没有管理多文件不卡死的资源管理工具","url":"/t/860695","author":"Routeros","node_url":"/go/windows","node_name":"Windows","replies":15,"avatar_url":"https://cdn.v2ex.com/avatar/8e3d/4efb/544300_large.png?m=1619898769","last_touched":"2022-06-19 22:57:15 +08:00","last_reply_by":"TsubasaHanekaw"},{"title":"开源 KV 引擎 NutsDB V0.9.0 发布~","url":"/t/860716","author":"xujiajun001","node_url":"/go/go","node_name":"Go 编程语言","replies":0,"avatar_url":"https://cdn.v2ex.com/avatar/c203/eec3/265667_large.png?m=1655643826","last_touched":"2022-06-19 21:15:28 +08:00","last_reply_by":""},{"title":"我们开发一款 RabbitMQ GUI 客户端，一键生成拓扑图，或许值得一试","url":"/t/860712","author":"likeunix","node_url":"/go/programmer","node_name":"程序员","replies":9,"avatar_url":"https://cdn.v2ex.com/gravatar/7c96f57e09f5768aeb701d1ebb6b7805?s=48&d=retro","last_touched":"2022-06-20 02:15:43 +08:00","last_reply_by":"Asjun"},{"title":"trzsz 已支持文件夹上传和下载，拖文件夹也会自动上传，支持多种平台的原生终端。","url":"/t/860713","author":"LonnyWong","node_url":"/go/programmer","node_name":"程序员","replies":0,"avatar_url":"https://cdn.v2ex.com/avatar/40a6/33a8/565001_xlarge.png?m=1647400608","last_touched":"2022-06-19 20:59:33 +08:00","last_reply_by":""},{"title":"折腾了一下自建短链接系统，感觉坑还不少","url":"/t/860613","author":"LxnChan","node_url":"/go/programmer","node_name":"程序员","replies":21,"avatar_url":"https://cdn.v2ex.com/gravatar/c27d945d034f2da687304f5ec6dab8ec?s=48&d=retro","last_touched":"2022-06-19 21:21:56 +08:00","last_reply_by":"LxnChan"},{"title":"Python 单列表等分为多列表小问题","url":"/t/860658","author":"leorealman","node_url":"/go/python","node_name":"Python","replies":15,"avatar_url":"https://cdn.v2ex.com/gravatar/27a4aa557858a0edd49823791a521288?s=48&d=retro","last_touched":"2022-06-19 20:33:02 +08:00","last_reply_by":"infun"},{"title":"给父母买保险有什么推荐的吗？","url":"/t/860660","author":"daoqiongsi1101","node_url":"/go/programmer","node_name":"程序员","replies":9,"avatar_url":"https://cdn.v2ex.com/avatar/18bc/5190/484283_large.png?m=1655623630","last_touched":"2022-06-20 06:11:09 +08:00","last_reply_by":"frankies"},{"title":"Back Pressed SearchView ActionView CollaspeActionView not work","url":"/t/860694","author":"KunMinX","node_url":"/go/android","node_name":"Android","replies":0,"avatar_url":"https://cdn.v2ex.com/avatar/bc09/4711/352257_large.png?m=1654794262","last_touched":"2022-06-19 18:24:19 +08:00","last_reply_by":""},{"title":"基于上次的 C 语言 http server，仿造做了一个文件上传下载功能。","url":"/t/860605","author":"microxiaoxiao","node_url":"/go/programmer","node_name":"程序员","replies":17,"avatar_url":"https://cdn.v2ex.com/gravatar/2b343cbcc00a1ed3d171b2aec6a5b4e5?s=48&d=retro","last_touched":"2022-06-19 22:49:18 +08:00","last_reply_by":"codehz"},{"title":"程序员下班时间的产出属于公司吗？","url":"/t/860394","author":"salor","node_url":"/go/programmer","node_name":"程序员","replies":64,"avatar_url":"https://cdn.v2ex.com/avatar/f14f/238e/470060_large.png?m=1647571721","last_touched":"2022-06-19 16:11:59 +08:00","last_reply_by":"bsfmig"},{"title":"VMware+ Ubantu20+ Cuttlefish 模拟运行最新的 Android12","url":"/t/860603","author":"FranzKafka95","node_url":"/go/android","node_name":"Android","replies":12,"avatar_url":"https://cdn.v2ex.com/gravatar/d37bf388e324a946bc0feab053281806?s=48&d=retro","last_touched":"2022-06-19 15:46:18 +08:00","last_reply_by":"junmoxiao"},{"title":"现在有没有几百块的备用安卓机","url":"/t/860566","author":"ruoyutx","node_url":"/go/android","node_name":"Android","replies":45,"avatar_url":"https://cdn.v2ex.com/gravatar/06cf315e82fa50ce1f2c5392e0f6cf63?s=48&d=retro","last_touched":"2022-06-19 22:27:34 +08:00","last_reply_by":"PostMeridiem18"},{"title":"kernel_task 占用 CPU 高达 3000%+，是不是硬件坏了","url":"/t/860615","author":"HeyHudy","node_url":"/go/programmer","node_name":"程序员","replies":13,"avatar_url":"https://cdn.v2ex.com/avatar/81c7/dc5a/530655_large.png?m=1655604402","last_touched":"2022-06-19 18:00:20 +08:00","last_reply_by":"lau52y"},{"title":"你真的需要一个 7x24 小时运行的 NAS 么？","url":"/t/860428","author":"2NUT","node_url":"/go/nas","node_name":"NAS","replies":107,"avatar_url":"https://cdn.v2ex.com/avatar/eadd/4c13/561069_large.png?m=1651500757","last_touched":"2022-06-20 01:59:08 +08:00","last_reply_by":"zhangdszq"},{"title":"有没有自动更新缓存的 DNS Server？","url":"/t/860548","author":"JiaNa","node_url":"/go/dns","node_name":"DNS","replies":15,"avatar_url":"https://cdn.v2ex.com/gravatar/00e618f9d1908398f53001a4d0192163?s=48&d=retro","last_touched":"2022-06-19 22:36:44 +08:00","last_reply_by":"bailliesun"},{"title":"gcc 为什么连这种代码都能编译通过？","url":"/t/860466","author":"kgdb00","node_url":"/go/linux","node_name":"Linux","replies":36,"avatar_url":"https://cdn.v2ex.com/gravatar/a5fb38dc1a69984a16c1b1c007b68172?s=48&d=retro","last_touched":"2022-06-19 17:22:12 +08:00","last_reply_by":"zxCoder"},{"title":"有道云笔记开始摆烂","url":"/t/860388","author":"documentzhangx66","node_url":"/go/programmer","node_name":"程序员","replies":18,"avatar_url":"https://cdn.v2ex.com/avatar/f59c/d92e/557492_large.png?m=1655654283","last_touched":"2022-06-20 00:10:01 +08:00","last_reply_by":"yagamil"},{"title":"RESTFul API 接口规范， GET 请求如何传递复杂对象？","url":"/t/860356","author":"dunhanson","node_url":"/go/programmer","node_name":"程序员","replies":70,"avatar_url":"https://cdn.v2ex.com/avatar/d2b2/2ccb/172659_large.png?m=1654673125","last_touched":"2022-06-19 23:09:36 +08:00","last_reply_by":"erquiasz0825"},{"title":"win10 开代理就不能有个提示吗","url":"/t/860487","author":"coyoteer","node_url":"/go/windows","node_name":"Windows","replies":26,"avatar_url":"https://cdn.v2ex.com/gravatar/622ef833c97c448dee475ea43c3b74d5?s=48&d=retro","last_touched":"2022-06-19 22:58:39 +08:00","last_reply_by":"Y29tL2gwd2Fy"},{"title":"大促 Z4 到手","url":"/t/860426","author":"ecloud","node_url":"/go/nas","node_name":"NAS","replies":33,"avatar_url":"https://cdn.v2ex.com/avatar/c430/bf33/151087_large.png?m=1654595603","last_touched":"2022-06-19 21:40:23 +08:00","last_reply_by":"cloverzrg2"},{"title":"有什么好用的电视盒子，求推荐","url":"/t/860054","author":"keyfunc","node_url":"/go/android","node_name":"Android","replies":74,"avatar_url":"https://cdn.v2ex.com/avatar/00e3/fc1d/21469_large.png?m=1647753406","last_touched":"2022-06-19 23:55:27 +08:00","last_reply_by":"06_taro"},{"title":"经过米家崩溃，想和大家讨论一下智能家居本地化的可能性。","url":"/t/860266","author":"LxnChan","node_url":"/go/programmer","node_name":"程序员","replies":117,"avatar_url":"https://cdn.v2ex.com/gravatar/c27d945d034f2da687304f5ec6dab8ec?s=48&d=retro","last_touched":"2022-06-19 18:06:20 +08:00","last_reply_by":"awsdocom"},{"title":"现在群晖系统里面，比较好的同步/下载 阿里云盘的 方法是什么？ docker？","url":"/t/860560","author":"yazoox","node_url":"/go/nas","node_name":"NAS","replies":11,"avatar_url":"https://cdn.v2ex.com/avatar/7b39/2690/111562_large.png?m=1635297358","last_touched":"2022-06-19 14:06:28 +08:00","last_reply_by":"panxiuqing"},{"title":"现在还有完全不开孔的 iPad 钢化膜吗？","url":"/t/860515","author":"ilxv","node_url":"/go/programmer","node_name":"程序员","replies":17,"avatar_url":"https://cdn.v2ex.com/avatar/cad1/859f/486400_xlarge.png?m=1653189466","last_touched":"2022-06-19 21:13:54 +08:00","last_reply_by":"ilxv"},{"title":"怎么确认系统是在以 10bit 模式显示内容","url":"/t/860523","author":"haoyh1","node_url":"/go/windows","node_name":"Windows","replies":11,"avatar_url":"https://cdn.v2ex.com/gravatar/1db3debddcb0b6aa2287ef70d1874277?s=48&d=retro","last_touched":"2022-06-19 00:22:22 +08:00","last_reply_by":"byzod"},{"title":"字节跳动 CDI 团队招人啦!","url":"/t/860404","author":"coderwff","node_url":"/go/programmer","node_name":"程序员","replies":27,"avatar_url":"https://cdn.v2ex.com/gravatar/cac27f60b8c6d89802990e72df911291?s=48&d=retro","last_touched":"2022-06-19 22:30:22 +08:00","last_reply_by":"leeg810312"},{"title":"目前有哪些使用 WinUI 3 的第三方软件？","url":"/t/860510","author":"szzhiyang","node_url":"/go/windows","node_name":"Windows","replies":3,"avatar_url":"https://cdn.v2ex.com/avatar/a14d/4c46/317258_xlarge.png?m=1646550609","last_touched":"2022-06-19 19:59:48 +08:00","last_reply_by":"terrytw"},{"title":"没想到在腾讯云上的服务器遭受到了来自腾讯云的重放攻击","url":"/t/860476","author":"NanoApe","node_url":"/go/programmer","node_name":"程序员","replies":15,"avatar_url":"https://cdn.v2ex.com/gravatar/3b80e77a4aa557756a0a55e81d0f1612?s=48&d=retro","last_touched":"2022-06-19 21:34:09 +08:00","last_reply_by":"SteveWoo"},{"title":"出一个 CleanMyMac X 永久版激活码","url":"/t/860546","author":"ilxv","node_url":"/go/programmer","node_name":"程序员","replies":4,"avatar_url":"https://cdn.v2ex.com/avatar/cad1/859f/486400_xlarge.png?m=1653189466","last_touched":"2022-06-19 21:52:55 +08:00","last_reply_by":"Chaconne"},{"title":"双拼输入法使用四年后容易忘记某键对应拼音","url":"/t/860256","author":"nosugar","node_url":"/go/programmer","node_name":"程序员","replies":87,"avatar_url":"https://cdn.v2ex.com/avatar/1fc6/2c8b/243529_large.png?m=1503053104","last_touched":"2022-06-19 14:09:34 +08:00","last_reply_by":"oxykr"},{"title":"typora 老版本开启强更，已换到 MarkText，但性能太差…","url":"/t/860011","author":"xshwy","node_url":"/go/markdown","node_name":"Markdown","replies":99,"avatar_url":"https://cdn.v2ex.com/avatar/83c1/3a1a/84323_large.png?m=1655205242","last_touched":"2022-06-19 21:50:39 +08:00","last_reply_by":"mudssky"},{"title":"安卓手机运行本地网页很慢，怎么解决？","url":"/t/860558","author":"ALLROBOT","node_url":"/go/programmer","node_name":"程序员","replies":3,"avatar_url":"https://cdn.v2ex.com/avatar/eb31/6d3f/333565_large.png?m=1650284643","last_touched":"2022-06-19 01:56:40 +08:00","last_reply_by":"ALLROBOT"},{"title":"gin 有没有类似 flask， django 这种缓存装饰器这样用法的？","url":"/t/860549","author":"yagamil","node_url":"/go/go","node_name":"Go 编程语言","replies":3,"avatar_url":"https://cdn.v2ex.com/avatar/e322/1a6d/318767_large.png?m=1612024295","last_touched":"2022-06-19 14:00:48 +08:00","last_reply_by":"janxin"},{"title":"[求助] typescript 的嵌套类型检查问题","url":"/t/860507","author":"yodhcn","node_url":"/go/programmer","node_name":"程序员","replies":7,"avatar_url":"https://cdn.v2ex.com/avatar/ac1d/d52e/504833_large.png?m=1655535764","last_touched":"2022-06-18 19:14:10 +08:00","last_reply_by":"luob"},{"title":"请问 Strapi 在国内自己 hosting 会有什么坑吗？","url":"/t/860277","author":"clouddd","node_url":"/go/nodejs","node_name":"Node.js","replies":6,"avatar_url":"https://cdn.v2ex.com/avatar/610c/eeb9/18940_xlarge.png?m=1642932412","last_touched":"2022-06-19 19:55:36 +08:00","last_reply_by":"joesonw"},{"title":"把/var/log 链接到 U 盘上会存在什么问题吗","url":"/t/860495","author":"LxnChan","node_url":"/go/linux","node_name":"Linux","replies":7,"avatar_url":"https://cdn.v2ex.com/gravatar/c27d945d034f2da687304f5ec6dab8ec?s=48&d=retro","last_touched":"2022-06-18 17:32:55 +08:00","last_reply_by":"Xusually"},{"title":"google 翻译也菠菜污染了","url":"/t/860408","author":"livenux","node_url":"/go/google","node_name":"Google","replies":19,"avatar_url":"https://cdn.v2ex.com/avatar/24f7/9017/289810_xlarge.png?m=1649921377","last_touched":"2022-06-19 16:50:02 +08:00","last_reply_by":"shequ2046"},{"title":"这样的火狐网页收藏插件应该怎样分享给他人使用？","url":"/t/860497","author":"i3x","node_url":"/go/programmer","node_name":"程序员","replies":2,"avatar_url":"https://cdn.v2ex.com/gravatar/fb7c2fbeaf06af0d4d8304fe4e2c4e2c?s=48&d=retro","last_touched":"2022-06-19 00:14:39 +08:00","last_reply_by":"hamsterbase"},{"title":"odoo 的 App Studio 是怎样实现的呢？","url":"/t/860471","author":"lyping","node_url":"/go/python","node_name":"Python","replies":4,"avatar_url":"https://cdn.v2ex.com/avatar/e9a8/f256/7358_large.png?m=1410406850","last_touched":"2022-06-18 20:47:55 +08:00","last_reply_by":"glovebx"}]}