{"fetchTime":1646265308896,"posts":[{"title":"请问数据库 Developer 有前途吗？","url":"/t/837523","author":"xiyangkevin","node_url":"/go/programmer","node_name":"程序员","replies":13,"avatar_url":"https://cdn.v2ex.com/gravatar/1b28bd8e426f94c7407cf213477b4025?s=48&d=retro","last_touched":"2022-03-03 07:52:15 +08:00","last_reply_by":"boshok"},{"title":"帮人安装服务器虚拟化系统+软路由系统，人工成本收费多少合适？","url":"/t/837517","author":"einsdisp","node_url":"/go/programmer","node_name":"程序员","replies":25,"avatar_url":"https://cdn.v2ex.com/gravatar/7533125b485db2a9a75aa3571c736e8c?s=48&d=retro","last_touched":"2022-03-03 07:51:11 +08:00","last_reply_by":"lemonda"},{"title":"你们公司涨工资会以职级提升为前提吗？","url":"/t/837572","author":"coolair","node_url":"/go/programmer","node_name":"程序员","replies":0,"avatar_url":"https://cdn.v2ex.com/avatar/c4fe/52ac/36118_large.png?m=1642386161","last_touched":"2022-03-03 07:45:31 +08:00","last_reply_by":""},{"title":"初中学历的 00 后程序员，未来怎么办？","url":"/t/837332","author":"kekeabab","node_url":"/go/programmer","node_name":"程序员","replies":183,"avatar_url":"https://cdn.v2ex.com/avatar/01d9/a29b/548222_large.png?m=1646181664","last_touched":"2022-03-03 07:39:38 +08:00","last_reply_by":"littlecreek"},{"title":"golang 框架 goal 征集 Logo 啦，设计大佬在哪里 ？","url":"/t/837433","author":"qbhy","node_url":"/go/go","node_name":"Go 编程语言","replies":13,"avatar_url":"https://cdn.v2ex.com/gravatar/461fe7f7ab23b18e209c027e72c5c00a?s=48&d=retro","last_touched":"2022-03-03 04:04:34 +08:00","last_reply_by":"dayeye2006199"},{"title":"为啥 macos 即使用了 sudo 也没办法运行 443 端口","url":"/t/837560","author":"MrF","node_url":"/go/nodejs","node_name":"Node.js","replies":3,"avatar_url":"https://cdn.v2ex.com/gravatar/920065ac2b4a6a67a72bb8f2aa11a4cd?s=48&d=retro","last_touched":"2022-03-03 03:08:50 +08:00","last_reply_by":"dangyuluo"},{"title":"荒野无灯大佬的 filebrowser 为啥不更新了，上一次是好几年前更新的了","url":"/t/837566","author":"monster33","node_url":"/go/programmer","node_name":"程序员","replies":2,"avatar_url":"https://cdn.v2ex.com/gravatar/d79486ef03ffd87194aee807083984d3?s=48&d=retro","last_touched":"2022-03-03 01:05:26 +08:00","last_reply_by":"ryon"},{"title":"2022 强力之作：一款超精致的图片预览组件","url":"/t/837557","author":"liumingyi1","node_url":"/go/react","node_name":"React","replies":3,"avatar_url":"https://cdn.v2ex.com/gravatar/0200ab0bf9668d0f948a50ba895c2d20?s=48&d=retro","last_touched":"2022-03-03 00:35:15 +08:00","last_reply_by":"TimPeake"},{"title":"斐波那契数列 n = 9292 的结果是什么？","url":"/t/837325","author":"CookCoder","node_url":"/go/programmer","node_name":"程序员","replies":63,"avatar_url":"https://cdn.v2ex.com/avatar/5f3f/0711/563360_large.png?m=1642042337","last_touched":"2022-03-03 00:31:17 +08:00","last_reply_by":"adoal"},{"title":"这个 VSCode 的鬼畜设计是怎么关闭的？","url":"/t/837343","author":"huanyingch01","node_url":"/go/vscode","node_name":"Visual Studio Code","replies":70,"avatar_url":"https://cdn.v2ex.com/gravatar/79383684868b6f811f60e2aeb62eab4a?s=48&d=retro","last_touched":"2022-03-03 00:27:36 +08:00","last_reply_by":"lysS"},{"title":"实例 down 掉， eureka 要 90s 后才剔除，那么期间的被打到这台实例的请求是不是就挂了？","url":"/t/837402","author":"yedra","node_url":"/go/java","node_name":"Java","replies":13,"avatar_url":"https://cdn.v2ex.com/avatar/b57c/62f5/242241_large.png?m=1638238929","last_touched":"2022-03-02 23:17:15 +08:00","last_reply_by":"plko345"},{"title":"MDN 突然改版","url":"/t/837283","author":"houzhenhong","node_url":"/go/webdev","node_name":"Web Dev","replies":54,"avatar_url":"https://cdn.v2ex.com/avatar/a47c/381e/110591_large.png?m=1646143306","last_touched":"2022-03-02 22:12:07 +08:00","last_reply_by":"initd"},{"title":"网络安全在读大学生暑假工","url":"/t/837535","author":"shihai314","node_url":"/go/security","node_name":"信息安全","replies":3,"avatar_url":"https://cdn.v2ex.com/gravatar/a5fc89882fc1faa9e1d183cd25cf7720?s=48&d=retro","last_touched":"2022-03-02 23:28:07 +08:00","last_reply_by":"shihai314"},{"title":"有什么办法可以将安卓电视的固件导出？","url":"/t/837558","author":"YOLObro","node_url":"/go/android","node_name":"Android","replies":2,"avatar_url":"https://cdn.v2ex.com/avatar/eb8d/0561/363682_xlarge.png?m=1642173484","last_touched":"2022-03-03 03:28:41 +08:00","last_reply_by":"ysc3839"},{"title":"为什么 git checkout 无法还原状态为 modify 的文件？","url":"/t/837503","author":"abcbuzhiming","node_url":"/go/git","node_name":"git","replies":7,"avatar_url":"https://cdn.v2ex.com/avatar/eced/0c34/112484_large.png?m=1640849018","last_touched":"2022-03-02 22:56:07 +08:00","last_reply_by":"rekulas"},{"title":"存在 OSS 上的 mp4 文件如何加密(禁止下载)","url":"/t/837508","author":"jiobanma","node_url":"/go/programmer","node_name":"程序员","replies":27,"avatar_url":"https://cdn.v2ex.com/avatar/581b/1335/487194_large.png?m=1601286723","last_touched":"2022-03-02 21:39:41 +08:00","last_reply_by":"wangfei324017"},{"title":"如何快速上手 vue？","url":"/t/837468","author":"ak8888","node_url":"/go/vue","node_name":"Vue.js","replies":14,"avatar_url":"https://cdn.v2ex.com/avatar/1d1a/7ccb/535758_large.png?m=1620281329","last_touched":"2022-03-02 19:25:45 +08:00","last_reply_by":"fkdtz"},{"title":"那种常受到促销 html 格式邮件，公司要求做，请问如何入手？","url":"/t/837307","author":"iGuChin","node_url":"/go/programmer","node_name":"程序员","replies":20,"avatar_url":"https://cdn.v2ex.com/gravatar/e8634e41ceb1fd340b6bc8f7c4b14b7c?s=48&d=retro","last_touched":"2022-03-02 18:43:14 +08:00","last_reply_by":"watcher"},{"title":"写了一个 golang 解析环境变量的工具库，准备用在生产里。","url":"/t/837450","author":"xmlHexagram","node_url":"/go/go","node_name":"Go 编程语言","replies":5,"avatar_url":"https://cdn.v2ex.com/avatar/0df3/69f7/552676_xlarge.png?m=1646205924","last_touched":"2022-03-02 23:28:31 +08:00","last_reply_by":"xmlHexagram"},{"title":"wordpress 开发 显示相关搜索关键词插件","url":"/t/837502","author":"Mattjim","node_url":"/go/php","node_name":"PHP","replies":4,"avatar_url":"https://cdn.v2ex.com/gravatar/9dd90115081ec864d57299882c2199c6?s=48&d=retro","last_touched":"2022-03-02 18:35:24 +08:00","last_reply_by":"theklf4"},{"title":"拖拽时默认的橡皮筋效果，它的参数从哪里获取呢？","url":"/t/837491","author":"sillydaddy","node_url":"/go/idev","node_name":"iDev","replies":4,"avatar_url":"https://cdn.v2ex.com/avatar/be86/c551/472822_large.png?m=1641892942","last_touched":"2022-03-03 07:34:59 +08:00","last_reply_by":"sillydaddy"},{"title":"固化硬盘数据无故丢失？没错,Windows 存在重大缺陷!","url":"/t/837426","author":"tiny1994095","node_url":"/go/windows","node_name":"Windows","replies":21,"avatar_url":"https://cdn.v2ex.com/avatar/e6ad/a642/458909_large.png?m=1576238432","last_touched":"2022-03-03 07:44:21 +08:00","last_reply_by":"tiny1994095"},{"title":"求助，天空卫士终端（mac）如何删除","url":"/t/837431","author":"superleexpert","node_url":"/go/security","node_name":"信息安全","replies":5,"avatar_url":"https://cdn.v2ex.com/avatar/a399/11c2/16959_large.png?m=1491456978","last_touched":"2022-03-02 17:52:09 +08:00","last_reply_by":"771007147"},{"title":"Django 线上项目 项目启动时使用了大量外键，一对一，一对多，多对多的关联， 现在需要去除外键依赖，该怎么去除？","url":"/t/837499","author":"bigpigB","node_url":"/go/python","node_name":"Python","replies":3,"avatar_url":"https://cdn.v2ex.com/gravatar/0e6322c6582a2e86732dc9e07f32f626?s=48&d=retro","last_touched":"2022-03-02 17:45:53 +08:00","last_reply_by":"youngce"},{"title":"Ubuntu 如何永久修改 MAC 地址？","url":"/t/837416","author":"LxnChan","node_url":"/go/linux","node_name":"Linux","replies":5,"avatar_url":"https://cdn.v2ex.com/gravatar/c27d945d034f2da687304f5ec6dab8ec?s=48&d=retro","last_touched":"2022-03-02 21:38:57 +08:00","last_reply_by":"thevita"},{"title":"现在购买 google one 之前相册使用过的空间会不会被扣掉","url":"/t/837428","author":"guabimian","node_url":"/go/google","node_name":"Google","replies":5,"avatar_url":"https://cdn.v2ex.com/gravatar/8a221e5577d57a4328696e2fa53937b8?s=48&d=retro","last_touched":"2022-03-02 16:34:02 +08:00","last_reply_by":"ruixue"},{"title":"开源程序该如何维护版权？！","url":"/t/837176","author":"mumuy","node_url":"/go/programmer","node_name":"程序员","replies":129,"avatar_url":"https://cdn.v2ex.com/avatar/0c41/250b/153538_large.png?m=1646117687","last_touched":"2022-03-02 16:53:19 +08:00","last_reply_by":"mumuy"},{"title":"nginx 限制单个 ip 请求次数是根据什么设置的？","url":"/t/837446","author":"justrand","node_url":"/go/nginx","node_name":"NGINX","replies":2,"avatar_url":"https://cdn.v2ex.com/gravatar/4fb68f6f965c975a322c085723bf4354?s=48&d=retro","last_touched":"2022-03-02 15:59:17 +08:00","last_reply_by":"justrand"},{"title":"国外大厂做这么多无法带来直接收益的项目的出发点是什么？","url":"/t/837145","author":"yoa1q7y","node_url":"/go/programmer","node_name":"程序员","replies":92,"avatar_url":"https://cdn.v2ex.com/avatar/7ce3/0f00/115394_large.png?m=1622803863","last_touched":"2022-03-02 19:16:10 +08:00","last_reply_by":"stoneabc"},{"title":"磁盘 Redis - Kvrocks 设计与实现","url":"/t/837321","author":"hulk","node_url":"/go/programmer","node_name":"程序员","replies":16,"avatar_url":"https://cdn.v2ex.com/avatar/fac4/bb38/30573_large.png?m=1419143710","last_touched":"2022-03-02 17:53:16 +08:00","last_reply_by":"hulk"},{"title":"在 Sqlite 中，怎么查询树形结构的 JSON 数据","url":"/t/837357","author":"tomatokiller","node_url":"/go/programmer","node_name":"程序员","replies":8,"avatar_url":"https://cdn.v2ex.com/gravatar/8f3bea07806ef457c61fbbc8c72c88be?s=48&d=retro","last_touched":"2022-03-02 11:46:06 +08:00","last_reply_by":"codehz"},{"title":"base 杭的，最近有 hc 嘛","url":"/t/837302","author":"Jackwang0127","node_url":"/go/programmer","node_name":"程序员","replies":13,"avatar_url":"https://cdn.v2ex.com/gravatar/46e7a1e0fc075118bfcadb03c7638921?s=48&d=retro","last_touched":"2022-03-03 00:47:15 +08:00","last_reply_by":"MarlonFan"},{"title":"前几天上 wc 时，站着等雨下时，手指无意识的虚点 2 下，手指肌肉记忆，突然就想起前面那个 OPPO 手机的密码了。太神奇了。","url":"/t/837270","author":"x500","node_url":"/go/programmer","node_name":"程序员","replies":19,"avatar_url":"https://cdn.v2ex.com/gravatar/3b1f13caa681a404c041cd8f4323b001?s=48&d=retro","last_touched":"2022-03-02 17:07:42 +08:00","last_reply_by":"brust"},{"title":"开坑 我准备开发一个可以在线养鱼钓鱼的地方","url":"/t/837070","author":"redtech","node_url":"/go/programmer","node_name":"程序员","replies":91,"avatar_url":"https://cdn.v2ex.com/avatar/e686/1954/569601_xlarge.png?m=1644995865","last_touched":"2022-03-02 16:05:40 +08:00","last_reply_by":"wangjhsir"},{"title":"Google Voice 回收机制","url":"/t/837196","author":"Knuth","node_url":"/go/google","node_name":"Google","replies":44,"avatar_url":"https://cdn.v2ex.com/gravatar/aea488b5566c4ef8fc574e316fb04ef2?s=48&d=retro","last_touched":"2022-03-03 06:44:13 +08:00","last_reply_by":"Sauman"},{"title":"MDN 改版了 https://hacks.mozilla.org/2022/03/a-new-year-a-new-mdn/","url":"/t/837441","author":"KouShuiYu","node_url":"/go/webdev","node_name":"Web Dev","replies":0,"avatar_url":"https://cdn.v2ex.com/avatar/a488/a9a9/463662_large.png?m=1643032001","last_touched":"2022-03-02 14:50:29 +08:00","last_reply_by":""},{"title":"大佬们，有谁研究过 Python importlib 机制？ sys.modules 缓存太大了","url":"/t/837192","author":"iyaozhen","node_url":"/go/python","node_name":"Python","replies":27,"avatar_url":"https://cdn.v2ex.com/avatar/6406/09f6/68154_large.png?m=1646119426","last_touched":"2022-03-02 16:25:30 +08:00","last_reply_by":"iyaozhen"},{"title":"一般而言个人项目在互联网上公开如何选择适合的协议？","url":"/t/837240","author":"mcfog","node_url":"/go/programmer","node_name":"程序员","replies":21,"avatar_url":"https://cdn.v2ex.com/avatar/442b/548e/7379_large.png?m=1330416855","last_touched":"2022-03-02 18:58:48 +08:00","last_reply_by":"wazon"},{"title":"全新的国产 golang 框架准备发布啦，快来看看吧","url":"/t/837246","author":"qbhy","node_url":"/go/go","node_name":"Go 编程语言","replies":29,"avatar_url":"https://cdn.v2ex.com/gravatar/461fe7f7ab23b18e209c027e72c5c00a?s=48&d=retro","last_touched":"2022-03-02 19:47:23 +08:00","last_reply_by":"qbhy"},{"title":"有上过培训班的老哥么，请教下。","url":"/t/836719","author":"Wzieee","node_url":"/go/programmer","node_name":"程序员","replies":177,"avatar_url":"https://cdn.v2ex.com/avatar/82f0/b490/303150_large.png?m=1610255430","last_touched":"2022-03-03 02:11:01 +08:00","last_reply_by":"chrosing"},{"title":"Debug 的时候又遇到这种灵异事件了","url":"/t/837189","author":"villivateur","node_url":"/go/programmer","node_name":"程序员","replies":16,"avatar_url":"https://cdn.v2ex.com/avatar/233d/26cb/273091_large.png?m=1644026564","last_touched":"2022-03-02 16:10:03 +08:00","last_reply_by":"wty"},{"title":"这是不是说明硬盘要坏了？","url":"/t/837133","author":"monster33","node_url":"/go/nas","node_name":"NAS","replies":19,"avatar_url":"https://cdn.v2ex.com/gravatar/d79486ef03ffd87194aee807083984d3?s=48&d=retro","last_touched":"2022-03-02 09:26:21 +08:00","last_reply_by":"superszy"},{"title":"求助一下现在 p2v 转换到 vmware 一般都用什么软件？","url":"/t/837331","author":"shequ2046","node_url":"/go/programmer","node_name":"程序员","replies":5,"avatar_url":"https://cdn.v2ex.com/avatar/6565/64ca/438761_large.png?m=1567135701","last_touched":"2022-03-03 01:03:03 +08:00","last_reply_by":"2NUT"},{"title":"键盘盲打一点问题也没有，拆下来后恢复却记不住键位，这是什么原理？","url":"/t/837226","author":"Morriaty","node_url":"/go/programmer","node_name":"程序员","replies":31,"avatar_url":"https://cdn.v2ex.com/avatar/64e7/d277/169110_large.png?m=1495696257","last_touched":"2022-03-02 17:19:08 +08:00","last_reply_by":"PepperEgg"},{"title":"新手机使用 google photos 备份照片一直处于“正在准备进行备份”的状态","url":"/t/837303","author":"lucacham","node_url":"/go/google","node_name":"Google","replies":4,"avatar_url":"https://cdn.v2ex.com/gravatar/58edd807692511b8a23129e5152d62c8?s=48&d=retro","last_touched":"2022-03-02 15:34:45 +08:00","last_reply_by":"lucacham"},{"title":"kubernetes（K8S）快速上手教程 + 实践","url":"/t/821329","author":"balabalaguguji","node_url":"/go/k8s","node_name":"Kubernetes","replies":72,"avatar_url":"https://cdn.v2ex.com/avatar/1383/cc45/341424_large.png?m=1635302395","last_touched":"2022-03-02 20:57:01 +08:00","last_reply_by":"balabalaguguji"},{"title":"哪些大型 Go 项目正在使用 Echo 框架？想学习一下它们的项目结构。","url":"/t/837248","author":"theklf4","node_url":"/go/go","node_name":"Go 编程语言","replies":11,"avatar_url":"https://cdn.v2ex.com/gravatar/4992f9ff63c26b4694fd1d2ca4e805e5?s=48&d=retro","last_touched":"2022-03-02 16:25:56 +08:00","last_reply_by":"lesismal"},{"title":"微信的 OAuth2.0 拿到的 access_token 除了获取用户信息，还能做什么呢","url":"/t/837031","author":"XiLemon","node_url":"/go/programmer","node_name":"程序员","replies":17,"avatar_url":"https://cdn.v2ex.com/gravatar/84af04d7078fb2df3fcced60e64bf214?s=48&d=retro","last_touched":"2022-03-02 20:09:03 +08:00","last_reply_by":"airyland"},{"title":"群晖 磁盘有坏道了，还能继续用么？","url":"/t/837274","author":"liangddyy","node_url":"/go/nas","node_name":"NAS","replies":7,"avatar_url":"https://cdn.v2ex.com/gravatar/714c55241198ab6b5ea579c41c6f5c16?s=48&d=retro","last_touched":"2022-03-02 23:59:51 +08:00","last_reply_by":"liangddyy"},{"title":"27 岁半路出家程序员确认慢性肾炎（CKD1），未来路在何方？","url":"/t/837009","author":"Fengyesuixiang","node_url":"/go/programmer","node_name":"程序员","replies":75,"avatar_url":"https://cdn.v2ex.com/avatar/edc3/e11e/417958_xlarge.png?m=1646055288","last_touched":"2022-03-02 20:02:48 +08:00","last_reply_by":"Fengyesuixiang"}]}